streamlit_heatmap/__init__.py
streamlit_heatmap/example.py
streamlit_heatmap/frontend/build/asset-manifest.json
streamlit_heatmap/frontend/build/bootstrap.min.css
streamlit_heatmap/frontend/build/index.html
streamlit_heatmap/frontend/build/static/css/main.7c2a3439.css
streamlit_heatmap/frontend/build/static/css/main.7c2a3439.css.map
streamlit_heatmap/frontend/build/static/js/main.147c12f2.js
streamlit_heatmap/frontend/build/static/js/main.147c12f2.js.LICENSE.txt
streamlit_heatmap/frontend/build/static/js/main.147c12f2.js.map
streamlit_heatmap_chart-0.0.1.dist-info/LICENSE
streamlit_heatmap_chart-0.0.1.dist-info/METADATA
streamlit_heatmap_chart-0.0.1.dist-info/WHEEL
streamlit_heatmap_chart-0.0.1.dist-info/top_level.txt
streamlit_heatmap_chart-0.0.1.dist-info/RECORD
